[
  {
    "team": "Dodgers",
    "team_abbr": "LAD",
    "division": "National League West",
    "elo_rating": 1621.6,
    "elo_change_7d": 19.1,
    "wins": 56,
    "losses": 30,
    "run_diff": 163,
    "playoff_probability": 1.0,
    "win_ds": 0.72,
    "win_cs": 0.44,
    "win_ws": 0.34
  },
  {
    "team": "Brewers",
    "team_abbr": "MIL",
    "division": "National League Central",
    "elo_rating": 1592.8,
    "elo_change_7d": -8.2,
    "wins": 52,
    "losses": 31,
    "run_diff": 127,
    "playoff_probability": 1.0,
    "win_ds": 0.63,
    "win_cs": 0.34,
    "win_ws": 0.23
  },
  {
    "team": "Rays",
    "team_abbr": "TB",
    "division": "American League East",
    "elo_rating": 1531.7,
    "elo_change_7d": 42.6,
    "wins": 49,
    "losses": 33,
    "run_diff": 30,
    "playoff_probability": 1.0,
    "win_ds": 0.61,
    "win_cs": 0.34,
    "win_ws": 0.09
  },
  {
    "team": "Braves",
    "team_abbr": "ATL",
    "division": "National League East",
    "elo_rating": 1490.4,
    "elo_change_7d": -22.3,
    "wins": 49,
    "losses": 34,
    "run_diff": 86,
    "playoff_probability": 0.931,
    "win_ds": 0.14,
    "win_cs": 0.02,
    "win_ws": 0.0
  },
  {
    "team": "Yankees",
    "team_abbr": "NYY",
    "division": "American League East",
    "elo_rating": 1493.0,
    "elo_change_7d": -70.7,
    "wins": 48,
    "losses": 37,
    "run_diff": 91,
    "playoff_probability": 1.0,
    "win_ds": 0.24,
    "win_cs": 0.09,
    "win_ws": 0.02
  },
  {
    "team": "Phillies",
    "team_abbr": "PHI",
    "division": "National League East",
    "elo_rating": 1586.9,
    "elo_change_7d": 1.7,
    "wins": 48,
    "losses": 38,
    "run_diff": 6,
    "playoff_probability": 0.689,
    "win_ds": 0.21,
    "win_cs": 0.08,
    "win_ws": 0.04
  },
  {
    "team": "Cubs",
    "team_abbr": "CHC",
    "division": "National League Central",
    "elo_rating": 1552.2,
    "elo_change_7d": 45.1,
    "wins": 48,
    "losses": 38,
    "run_diff": 43,
    "playoff_probability": 0.767,
    "win_ds": 0.14,
    "win_cs": 0.06,
    "win_ws": 0.04
  },
  {
    "team": "White Sox",
    "team_abbr": "CWS",
    "division": "American League Central",
    "elo_rating": 1540.2,
    "elo_change_7d": 19.2,
    "wins": 45,
    "losses": 39,
    "run_diff": 30,
    "playoff_probability": 0.764,
    "win_ds": 0.48,
    "win_cs": 0.28,
    "win_ws": 0.12
  },
  {
    "team": "Marlins",
    "team_abbr": "MIA",
    "division": "National League East",
    "elo_rating": 1575.6,
    "elo_change_7d": 20.2,
    "wins": 46,
    "losses": 40,
    "run_diff": 24,
    "playoff_probability": 0.317,
    "win_ds": 0.11,
    "win_cs": 0.05,
    "win_ws": 0.03
  },
  {
    "team": "Cardinals",
    "team_abbr": "STL",
    "division": "National League Central",
    "elo_rating": 1497.2,
    "elo_change_7d": 5.5,
    "wins": 44,
    "losses": 38,
    "run_diff": -6,
    "playoff_probability": 0.282,
    "win_ds": 0.03,
    "win_cs": 0.0,
    "win_ws": 0.0
  },
  {
    "team": "Guardians",
    "team_abbr": "CLE",
    "division": "American League Central",
    "elo_rating": 1487.6,
    "elo_change_7d": -13.9,
    "wins": 44,
    "losses": 42,
    "run_diff": -13,
    "playoff_probability": 0.358,
    "win_ds": 0.18,
    "win_cs": 0.04,
    "win_ws": 0.02
  },
  {
    "team": "Rangers",
    "team_abbr": "TEX",
    "division": "American League West",
    "elo_rating": 1537.6,
    "elo_change_7d": 65.6,
    "wins": 44,
    "losses": 42,
    "run_diff": -3,
    "playoff_probability": 0.491,
    "win_ds": 0.19,
    "win_cs": 0.12,
    "win_ws": 0.06
  },
  {
    "team": "Padres",
    "team_abbr": "SD",
    "division": "National League West",
    "elo_rating": 1490.7,
    "elo_change_7d": -21.9,
    "wins": 43,
    "losses": 41,
    "run_diff": -16,
    "playoff_probability": 0.104,
    "win_ds": 0.01,
    "win_cs": 0.0,
    "win_ws": 0.0
  },
  {
    "team": "Mariners",
    "team_abbr": "SEA",
    "division": "American League West",
    "elo_rating": 1502.9,
    "elo_change_7d": 0.1,
    "wins": 44,
    "losses": 43,
    "run_diff": 13,
    "playoff_probability": 0.397,
    "win_ds": 0.15,
    "win_cs": 0.09,
    "win_ws": 0.0
  },
  {
    "team": "Nationals",
    "team_abbr": "WSH",
    "division": "National League East",
    "elo_rating": 1510.9,
    "elo_change_7d": 5.9,
    "wins": 44,
    "losses": 43,
    "run_diff": 9,
    "playoff_probability": 0.081,
    "win_ds": 0.01,
    "win_cs": 0.01,
    "win_ws": 0.0
  },
  {
    "team": "D-backs",
    "team_abbr": "AZ",
    "division": "National League West",
    "elo_rating": 1489.0,
    "elo_change_7d": -7.1,
    "wins": 43,
    "losses": 42,
    "run_diff": -24,
    "playoff_probability": 0.081,
    "win_ds": 0.0,
    "win_cs": 0.0,
    "win_ws": 0.0
  },
  {
    "team": "Pirates",
    "team_abbr": "PIT",
    "division": "National League Central",
    "elo_rating": 1490.6,
    "elo_change_7d": 1.9,
    "wins": 43,
    "losses": 43,
    "run_diff": 24,
    "playoff_probability": 0.063,
    "win_ds": 0.0,
    "win_cs": 0.0,
    "win_ws": 0.0
  },
  {
    "team": "Astros",
    "team_abbr": "HOU",
    "division": "American League West",
    "elo_rating": 1524.8,
    "elo_change_7d": 12.5,
    "wins": 43,
    "losses": 45,
    "run_diff": -41,
    "playoff_probability": 0.204,
    "win_ds": 0.1,
    "win_cs": 0.04,
    "win_ws": 0.01
  },
  {
    "team": "Twins",
    "team_abbr": "MIN",
    "division": "American League Central",
    "elo_rating": 1482.4,
    "elo_change_7d": 7.5,
    "wins": 41,
    "losses": 46,
    "run_diff": -31,
    "playoff_probability": 0.029,
    "win_ds": 0.01,
    "win_cs": 0.0,
    "win_ws": 0.0
  },
  {
    "team": "Blue Jays",
    "team_abbr": "TOR",
    "division": "American League East",
    "elo_rating": 1463.9,
    "elo_change_7d": -48.6,
    "wins": 40,
    "losses": 46,
    "run_diff": -35,
    "playoff_probability": 0.022,
    "win_ds": 0.01,
    "win_cs": 0.0,
    "win_ws": 0.0
  },
  {
    "team": "Athletics",
    "team_abbr": "ATH",
    "division": "American League West",
    "elo_rating": 1441.1,
    "elo_change_7d": -8.7,
    "wins": 40,
    "losses": 46,
    "run_diff": -65,
    "playoff_probability": 0.079,
    "win_ds": 0.03,
    "win_cs": 0.0,
    "win_ws": 0.0
  },
  {
    "team": "Reds",
    "team_abbr": "CIN",
    "division": "National League Central",
    "elo_rating": 1456.8,
    "elo_change_7d": 3.1,
    "wins": 39,
    "losses": 45,
    "run_diff": -58,
    "playoff_probability": 0.0,
    "win_ds": 0.0,
    "win_cs": 0.0,
    "win_ws": 0.0
  },
  {
    "team": "Orioles",
    "team_abbr": "BAL",
    "division": "American League East",
    "elo_rating": 1458.8,
    "elo_change_7d": -31.9,
    "wins": 39,
    "losses": 48,
    "run_diff": -38,
    "playoff_probability": 0.004,
    "win_ds": 0.0,
    "win_cs": 0.0,
    "win_ws": 0.0
  },
  {
    "team": "Red Sox",
    "team_abbr": "BOS",
    "division": "American League East",
    "elo_rating": 1492.2,
    "elo_change_7d": 43.4,
    "wins": 37,
    "losses": 47,
    "run_diff": 1,
    "playoff_probability": 0.0,
    "win_ds": 0.0,
    "win_cs": 0.0,
    "win_ws": 0.0
  },
  {
    "team": "Tigers",
    "team_abbr": "DET",
    "division": "American League Central",
    "elo_rating": 1464.6,
    "elo_change_7d": 9.1,
    "wins": 37,
    "losses": 49,
    "run_diff": 7,
    "playoff_probability": 0.0,
    "win_ds": 0.0,
    "win_cs": 0.0,
    "win_ws": 0.0
  },
  {
    "team": "Mets",
    "team_abbr": "NYM",
    "division": "National League East",
    "elo_rating": 1444.8,
    "elo_change_7d": -5.5,
    "wins": 36,
    "losses": 50,
    "run_diff": -43,
    "playoff_probability": 0.0,
    "win_ds": 0.0,
    "win_cs": 0.0,
    "win_ws": 0.0
  },
  {
    "team": "Angels",
    "team_abbr": "LAA",
    "division": "American League West",
    "elo_rating": 1453.0,
    "elo_change_7d": -8.9,
    "wins": 36,
    "losses": 51,
    "run_diff": -45,
    "playoff_probability": 0.0,
    "win_ds": 0.0,
    "win_cs": 0.0,
    "win_ws": 0.0
  },
  {
    "team": "Giants",
    "team_abbr": "SF",
    "division": "National League West",
    "elo_rating": 1466.8,
    "elo_change_7d": -19.5,
    "wins": 35,
    "losses": 50,
    "run_diff": -57,
    "playoff_probability": 0.0,
    "win_ds": 0.0,
    "win_cs": 0.0,
    "win_ws": 0.0
  },
  {
    "team": "Royals",
    "team_abbr": "KC",
    "division": "American League Central",
    "elo_rating": 1444.2,
    "elo_change_7d": -17.6,
    "wins": 35,
    "losses": 51,
    "run_diff": -76,
    "playoff_probability": 0.0,
    "win_ds": 0.0,
    "win_cs": 0.0,
    "win_ws": 0.0
  },
  {
    "team": "Rockies",
    "team_abbr": "COL",
    "division": "National League West",
    "elo_rating": 1415.7,
    "elo_change_7d": -17.5,
    "wins": 33,
    "losses": 53,
    "run_diff": -103,
    "playoff_probability": 0.0,
    "win_ds": 0.0,
    "win_cs": 0.0,
    "win_ws": 0.0
  }
]