{
  "AZ": [
    {
      "date": "season-start",
      "rating": 1499.1
    }
  ],
  "SF": [
    {
      "date": "season-start",
      "rating": 1493.6
    }
  ],
  "BOS": [
    {
      "date": "season-start",
      "rating": 1520.6
    }
  ],
  "CLE": [
    {
      "date": "season-start",
      "rating": 1524.4
    }
  ],
  "BAL": [
    {
      "date": "season-start",
      "rating": 1501.6
    }
  ],
  "ATH": [
    {
      "date": "season-start",
      "rating": 1504.8
    }
  ],
  "KC": [
    {
      "date": "season-start",
      "rating": 1506.8
    }
  ],
  "MIA": [
    {
      "date": "season-start",
      "rating": 1508.7
    }
  ],
  "MIL": [
    {
      "date": "season-start",
      "rating": 1515.5
    }
  ],
  "PIT": [
    {
      "date": "season-start",
      "rating": 1497.7
    }
  ],
  "MIN": [
    {
      "date": "season-start",
      "rating": 1472.4
    }
  ],
  "NYM": [
    {
      "date": "season-start",
      "rating": 1487.2
    }
  ],
  "TB": [
    {
      "date": "season-start",
      "rating": 1484.3
    }
  ],
  "ATL": [
    {
      "date": "season-start",
      "rating": 1505.2
    }
  ],
  "SEA": [
    {
      "date": "season-start",
      "rating": 1522.4
    }
  ],
  "TOR": [
    {
      "date": "season-start",
      "rating": 1521.1
    }
  ],
  "HOU": [
    {
      "date": "season-start",
      "rating": 1502.4
    }
  ],
  "CWS": [
    {
      "date": "season-start",
      "rating": 1474.7
    }
  ],
  "SD": [
    {
      "date": "season-start",
      "rating": 1507.8
    }
  ],
  "STL": [
    {
      "date": "season-start",
      "rating": 1484.8
    }
  ],
  "LAA": [
    {
      "date": "season-start",
      "rating": 1466.8
    }
  ],
  "CIN": [
    {
      "date": "season-start",
      "rating": 1506.7
    }
  ],
  "PHI": [
    {
      "date": "season-start",
      "rating": 1526.1
    }
  ],
  "COL": [
    {
      "date": "season-start",
      "rating": 1439.0
    }
  ],
  "WSH": [
    {
      "date": "season-start",
      "rating": 1475.7
    }
  ],
  "LAD": [
    {
      "date": "season-start",
      "rating": 1526.1
    }
  ],
  "CHC": [
    {
      "date": "season-start",
      "rating": 1507.6
    }
  ],
  "DET": [
    {
      "date": "season-start",
      "rating": 1484.7
    }
  ],
  "TEX": [
    {
      "date": "season-start",
      "rating": 1493.8
    }
  ],
  "NYY": [
    {
      "date": "season-start",
      "rating": 1538.3
    }
  ]
}